odoo10_addon_auth_supplier-10.0.1.0.0-py2.7-nspkg.pth
odoo/addons/auth_supplier/README.rst
odoo/addons/auth_supplier/__init__.py
odoo/addons/auth_supplier/__manifest__.py
odoo/addons/auth_supplier/controllers/__init__.py
odoo/addons/auth_supplier/controllers/main.py
odoo/addons/auth_supplier/i18n/bg.po
odoo/addons/auth_supplier/i18n/de.po
odoo/addons/auth_supplier/i18n/el_GR.po
odoo/addons/auth_supplier/i18n/es.po
odoo/addons/auth_supplier/i18n/es_MX.po
odoo/addons/auth_supplier/i18n/eu_ES.po
odoo/addons/auth_supplier/i18n/fi.po
odoo/addons/auth_supplier/i18n/fr.po
odoo/addons/auth_supplier/i18n/fr_FR.po
odoo/addons/auth_supplier/i18n/gl.po
odoo/addons/auth_supplier/i18n/hr.po
odoo/addons/auth_supplier/i18n/hr_HR.po
odoo/addons/auth_supplier/i18n/it.po
odoo/addons/auth_supplier/i18n/nl.po
odoo/addons/auth_supplier/i18n/nl_NL.po
odoo/addons/auth_supplier/i18n/pt_BR.po
odoo/addons/auth_supplier/i18n/pt_PT.po
odoo/addons/auth_supplier/i18n/sk.po
odoo/addons/auth_supplier/i18n/sl.po
odoo/addons/auth_supplier/i18n/tr.po
odoo/addons/auth_supplier/i18n/zh_CN.po
odoo/addons/auth_supplier/static/description/icon.png
odoo/addons/auth_supplier/views/auth_supplier_view.xml
odoo10_addon_auth_supplier-10.0.1.0.0.dist-info/DESCRIPTION.rst
odoo10_addon_auth_supplier-10.0.1.0.0.dist-info/METADATA
odoo10_addon_auth_supplier-10.0.1.0.0.dist-info/RECORD
odoo10_addon_auth_supplier-10.0.1.0.0.dist-info/WHEEL
odoo10_addon_auth_supplier-10.0.1.0.0.dist-info/metadata.json
odoo10_addon_auth_supplier-10.0.1.0.0.dist-info/namespace_packages.txt
odoo10_addon_auth_supplier-10.0.1.0.0.dist-info/top_level.txt
